_pahmm_cffi.abi3.so
pahmm/__init__.py
pahmm/libpahmm.so
pahmm-0.1.2.dist-info/RECORD
pahmm-0.1.2.dist-info/top_level.txt
pahmm-0.1.2.dist-info/LICENSE
pahmm-0.1.2.dist-info/WHEEL
pahmm-0.1.2.dist-info/METADATA
pahmm.libs/libsqlite3-d382f174.so.0.8.6
