Metadata-Version: 2.1
Name: pahmm
Version: 0.1.2
Summary: Pairwise statistical phylogenetic distance estimation using pair hidden Markov models for Python.
Home-page: https://github.com/mazen-mardini/libpahmm
Author: Mazen Mardini
Author-email: mazen@mengate.se
License: UNKNOWN
Platform: UNKNOWN
Classifier: Topic :: Scientific/Engineering :: Bio-Informatics
Classifier: Programming Language :: Python :: 3
Classifier: Programming Language :: C
Classifier: Natural Language :: English
Classifier: License :: OSI Approved :: GNU General Public License v3 (GPLv3)
Classifier: Operating System :: POSIX :: Linux
Requires-Python: >=3.6
License-File: LICENSE
